<annotation><folder>pk_labels/</folder><filename>apk00168632.jpg</filename><path>./imagesapk00168632.jpg</path><source><database>Unknown</database></source><size><width>600</width><height>383</height><depth>3</depth></size><object><name>Fname</name><truncated>0</truncated><difficult>0</difficult><bndbox><xmin>386</xmin><ymin>0</ymin><xmax>507</xmax><ymax>44</ymax></bndbox></object><object><name>Lname</name><truncated>0</truncated><difficult>0</difficult><bndbox><xmin>491</xmin><ymin>20</ymin><xmax>540</xmax><ymax>66</ymax></bndbox></object><object><name>gender</name><truncated>0</truncated><difficult>0</difficult><bndbox><xmin>283</xmin><ymin>99</ymin><xmax>314</xmax><ymax>130</ymax></bndbox></object><object><name>IDnumber</name><truncated>0</truncated><difficult>0</difficult><bndbox><xmin>254</xmin><ymin>143</ymin><xmax>389</xmax><ymax>246</ymax></bndbox></object><object><name>DOB</name><truncated>0</truncated><difficult>0</difficult><bndbox><xmin>393</xmin><ymin>238</ymin><xmax>483</xmax><ymax>309</ymax></bndbox></object><object><name>nationality</name><truncated>0</truncated><difficult>0</difficult><bndbox><xmin>62</xmin><ymin>0</ymin><xmax>600</xmax><ymax>383</ymax></bndbox></object></annotation>