<annotation><folder>sp_labels/</folder><filename>spimages (2)210.jpg</filename><path>./imagesspimages (2)210.jpg</path><source><database>Unknown</database></source><size><width>281</width><height>179</height><depth>3</depth></size><object><name>nationality</name><truncated>0</truncated><difficult>0</difficult><bndbox><xmin>139</xmin><ymin>50</ymin><xmax>201</xmax><ymax>64</ymax></bndbox></object><object><name>Fname</name><truncated>0</truncated><difficult>0</difficult><bndbox><xmin>139</xmin><ymin>98</ymin><xmax>216</xmax><ymax>109</ymax></bndbox></object><object><name>Lname</name><truncated>0</truncated><difficult>0</difficult><bndbox><xmin>219</xmin><ymin>101</ymin><xmax>255</xmax><ymax>112</ymax></bndbox></object><object><name>DOB</name><truncated>0</truncated><difficult>0</difficult><bndbox><xmin>136</xmin><ymin>150</ymin><xmax>177</xmax><ymax>160</ymax></bndbox></object><object><name>IDnumber</name><truncated>0</truncated><difficult>0</difficult><bndbox><xmin>145</xmin><ymin>64</ymin><xmax>209</xmax><ymax>77</ymax></bndbox></object><object><name>gender</name><truncated>0</truncated><difficult>0</difficult><bndbox><xmin>184</xmin><ymin>154</ymin><xmax>190</xmax><ymax>159</ymax></bndbox></object></annotation>