<annotation><folder>us_labels/</folder><filename>us48832632553_2f7a6aef66_o212.jpg</filename><path>./imagesus48832632553_2f7a6aef66_o212.jpg</path><source><database>Unknown</database></source><size><width>600</width><height>390</height><depth>3</depth></size><object><name>Lname</name><truncated>0</truncated><difficult>0</difficult><bndbox><xmin>293</xmin><ymin>151</ymin><xmax>370</xmax><ymax>217</ymax></bndbox></object><object><name>Fname</name><truncated>0</truncated><difficult>0</difficult><bndbox><xmin>269</xmin><ymin>185</ymin><xmax>327</xmax><ymax>237</ymax></bndbox></object><object><name>IDnumber</name><truncated>0</truncated><difficult>0</difficult><bndbox><xmin>447</xmin><ymin>248</ymin><xmax>532</xmax><ymax>320</ymax></bndbox></object><object><name>DOB</name><truncated>0</truncated><difficult>0</difficult><bndbox><xmin>332</xmin><ymin>315</ymin><xmax>414</xmax><ymax>386</ymax></bndbox></object><object><name>gender</name><truncated>0</truncated><difficult>0</difficult><bndbox><xmin>305</xmin><ymin>296</ymin><xmax>335</xmax><ymax>326</ymax></bndbox></object><object><name>nationality</name><truncated>0</truncated><difficult>0</difficult><bndbox><xmin>402</xmin><ymin>212</ymin><xmax>440</xmax><ymax>247</ymax></bndbox></object></annotation>