<annotation><folder>us_labels/</folder><filename>us522de527c8fd0c20bede6b1a3c8f5d63730.jpg</filename><path>./imagesus522de527c8fd0c20bede6b1a3c8f5d63730.jpg</path><source><database>Unknown</database></source><size><width>600</width><height>422</height><depth>3</depth></size><object><name>nationality</name><truncated>0</truncated><difficult>0</difficult><bndbox><xmin>543</xmin><ymin>88</ymin><xmax>570</xmax><ymax>146</ymax></bndbox></object><object><name>IDnumber</name><truncated>0</truncated><difficult>0</difficult><bndbox><xmin>570</xmin><ymin>273</ymin><xmax>600</xmax><ymax>399</ymax></bndbox></object><object><name>Lname</name><truncated>0</truncated><difficult>0</difficult><bndbox><xmin>501</xmin><ymin>83</ymin><xmax>538</xmax><ymax>204</ymax></bndbox></object><object><name>Fname</name><truncated>0</truncated><difficult>0</difficult><bndbox><xmin>469</xmin><ymin>133</ymin><xmax>507</xmax><ymax>233</ymax></bndbox></object><object><name>DOB</name><truncated>0</truncated><difficult>0</difficult><bndbox><xmin>439</xmin><ymin>206</ymin><xmax>481</xmax><ymax>324</ymax></bndbox></object><object><name>gender</name><truncated>0</truncated><difficult>0</difficult><bndbox><xmin>434</xmin><ymin>155</ymin><xmax>453</xmax><ymax>178</ymax></bndbox></object></annotation>