<annotation><folder>uk_labels/</folder><filename>uk-Small65.jpg</filename><path>./imagesuk-Small65.jpg</path><source><database>Unknown</database></source><size><width>600</width><height>381</height><depth>3</depth></size><object><name>IDnumber</name><truncated>0</truncated><difficult>0</difficult><bndbox><xmin>407</xmin><ymin>204</ymin><xmax>482</xmax><ymax>304</ymax></bndbox></object><object><name>Lname</name><truncated>0</truncated><difficult>0</difficult><bndbox><xmin>169</xmin><ymin>0</ymin><xmax>253</xmax><ymax>59</ymax></bndbox></object><object><name>Fname</name><truncated>0</truncated><difficult>0</difficult><bndbox><xmin>154</xmin><ymin>0</ymin><xmax>213</xmax><ymax>37</ymax></bndbox></object><object><name>nationality</name><truncated>0</truncated><difficult>0</difficult><bndbox><xmin>192</xmin><ymin>160</ymin><xmax>241</xmax><ymax>220</ymax></bndbox></object><object><name>gender</name><truncated>0</truncated><difficult>0</difficult><bndbox><xmin>153</xmin><ymin>100</ymin><xmax>177</xmax><ymax>125</ymax></bndbox></object><object><name>DOB</name><truncated>0</truncated><difficult>0</difficult><bndbox><xmin>122</xmin><ymin>119</ymin><xmax>212</xmax><ymax>239</ymax></bndbox></object></annotation>